du_aio_tools/Iterator_xml.py
du_aio_tools/__init__.py
du_aio_tools/attr_dict.py
du_aio_tools/base_conn.py
du_aio_tools/base_spider.py
du_aio_tools/exceptions.py
du_aio_tools/rsa.py
du_aio_tools/schemas.py
du_aio_tools/time.py
du_aio_tools-0.0.19.dist-info/METADATA
du_aio_tools-0.0.19.dist-info/WHEEL
du_aio_tools-0.0.19.dist-info/top_level.txt
du_aio_tools-0.0.19.dist-info/RECORD
