Metadata-Version: 2.4
Name: du-aio-tools
Version: 0.0.19
Summary: async tools
Requires-Python: >=3.7
Requires-Dist: fake-useragent
Requires-Dist: httpx
Requires-Dist: pycryptodome
Requires-Dist: pydantic>=2.0
Requires-Dist: python-dotenv
Requires-Dist: pyyaml
Requires-Dist: requests
Requires-Dist: setuptools
Requires-Dist: tenacity
